README.md
setup.py
ccb/__init__.py
ccb/__main__.py
ccb/_version.py
ccb/cci.py
ccb/git.py
ccb/github.py
ccb/issue.py
ccb/project_specifics.py
ccb/recipe.py
ccb/status.py
ccb/subprocess.py
ccb/upstream_project.py
ccb/utils.py
ccb/version.py
ccb/yaml.py
ccb/update/__init__.py
ccb/update/auto.py
ccb/update/common.py
ccb/update/manual.py
conan_center_bot.egg-info/PKG-INFO
conan_center_bot.egg-info/SOURCES.txt
conan_center_bot.egg-info/dependency_links.txt
conan_center_bot.egg-info/entry_points.txt
conan_center_bot.egg-info/requires.txt
conan_center_bot.egg-info/top_level.txt