Metadata-Version: 2.1
Name: conan-center-bot
Version: 0.3.0
Summary: A bot to automatically update conan-center-index
Home-page: https://github.com/qchateau/conan-center-bot
Author: Quentin Chateau
Author-email: quentin.chateau@gmail.com
License: GPLv3
Platform: UNKNOWN
Classifier: Development Status :: 1 - Planning
Classifier: Programming Language :: Python :: 3
Classifier: Programming Language :: C
Classifier: Programming Language :: C++
Classifier: License :: OSI Approved :: GNU General Public License v3 or later (GPLv3+)
Classifier: Operating System :: OS Independent
Requires-Python: >=3.7
